curation_utils/__init__.py
curation_utils/archive_utility.py
curation_utils/dir_helper.py
curation_utils/list_helper.py
curation_utils/scraping.py
curation_utils/file_helper/__init__.py
curation_utils/file_helper/multi_file_reader.py
curation_utils/google/__init__.py
curation_utils/google/api_helper.py
curation_utils/google/drive.py
curation_utils/google/sheets.py
curation_utils-0.2.10.dist-info/LICENSE.txt
curation_utils-0.2.10.dist-info/METADATA
curation_utils-0.2.10.dist-info/WHEEL
curation_utils-0.2.10.dist-info/top_level.txt
curation_utils-0.2.10.dist-info/RECORD
