Metadata-Version: 2.1
Name: curation-utils
Version: 0.2.10
Summary: Miscellaneous curation scripts.
Home-page: https://github.com/sanskrit-coders/curation_utils
Author: Sanskrit programmers
Author-email: sanskrit-programmers@googlegroups.com
License: MIT
Keywords: audio internet-archive
Platform: UNKNOWN
Classifier: Development Status :: 5 - Production/Stable
Classifier: Intended Audience :: Education
Classifier: Topic :: Text Processing :: Linguistic
Classifier: License :: OSI Approved :: MIT License
Classifier: Programming Language :: Python :: 3
Classifier: Programming Language :: Python :: 3.8
License-File: LICENSE.txt
Requires-Dist: httpx
Requires-Dist: gspread
Requires-Dist: oauth2client
Requires-Dist: pandas
Requires-Dist: wget
Requires-Dist: requests
Requires-Dist: bs4
Requires-Dist: beautifulsoup4
Requires-Dist: selenium
Requires-Dist: urllib3
Requires-Dist: regex
Requires-Dist: pypandoc
Requires-Dist: setuptools
Requires-Dist: chardet
Requires-Dist: indic-transliteration
Requires-Dist: tqdm
Requires-Dist: backoff
Provides-Extra: all
Requires-Dist: httpx ; extra == 'all'
Requires-Dist: gspread ; extra == 'all'
Requires-Dist: oauth2client ; extra == 'all'
Requires-Dist: pandas ; extra == 'all'
Requires-Dist: wget ; extra == 'all'
Requires-Dist: requests ; extra == 'all'
Requires-Dist: bs4 ; extra == 'all'
Requires-Dist: beautifulsoup4 ; extra == 'all'
Requires-Dist: selenium ; extra == 'all'
Requires-Dist: urllib3 ; extra == 'all'
Requires-Dist: regex ; extra == 'all'
Requires-Dist: pypandoc ; extra == 'all'
Requires-Dist: setuptools ; extra == 'all'
Requires-Dist: chardet ; extra == 'all'
Requires-Dist: indic-transliteration ; extra == 'all'
Requires-Dist: tqdm ; extra == 'all'
Requires-Dist: backoff ; extra == 'all'
Requires-Dist: internetarchive ; extra == 'all'
Requires-Dist: google-auth-oauthlib ; extra == 'all'
Requires-Dist: google-api-python-client ; extra == 'all'
Requires-Dist: google-auth-httplib2 ; extra == 'all'
Requires-Dist: google ; extra == 'all'
Provides-Extra: extras
Requires-Dist: internetarchive ; extra == 'extras'
Requires-Dist: google-auth-oauthlib ; extra == 'extras'
Requires-Dist: google-api-python-client ; extra == 'extras'
Requires-Dist: google-auth-httplib2 ; extra == 'extras'
Requires-Dist: google ; extra == 'extras'
Provides-Extra: test
Requires-Dist: pytest ; extra == 'test'
